tf_train/__init__.py
tf_train/api.py
tf_train/train_loop.py
tf_train/utils.py
tf_train-1.3.0.dist-info/LICENSE
tf_train-1.3.0.dist-info/METADATA
tf_train-1.3.0.dist-info/WHEEL
tf_train-1.3.0.dist-info/top_level.txt
tf_train-1.3.0.dist-info/RECORD
