Metadata-Version: 2.1
Name: tf-train
Version: 1.3.0
Summary: Additional package for Tensorflow
Home-page: https://github.com/TheDim0n/TensorflowTraining
Author: TheDim0n
License: MIT
Platform: UNKNOWN
Requires-Python: >=3.6
Requires-Dist: tensorflow (==2.2)
